{"doc":" 通知渠道策略工厂\n","fields":[],"enumConstants":[],"methods":[{"name":"getStrategy","paramTypes":["java.lang.String"],"doc":" 获取通知渠道策略\n\n @param channelCode 渠道代码\n @return 渠道策略\n"},{"name":"getAllStrategies","paramTypes":[],"doc":" 获取所有可用的渠道策略\n\n @return 渠道策略映射表\n"},{"name":"getAllChannelCodes","paramTypes":[],"doc":" 获取所有可用的渠道代码\n\n @return 渠道代码集合\n"},{"name":"getEnabledChannelsForUser","paramTypes":["java.lang.Long","java.util.Map","java.lang.String"],"doc":" 获取用户启用的渠道\n\n @param userId           用户ID\n @param userSettings     用户设置\n @param notificationType 通知类型\n @return 启用的渠道列表\n"},{"name":"hasChannel","paramTypes":["java.lang.String"],"doc":" 判断渠道是否存在\n\n @param channelCode 渠道代码\n @return 是否存在\n"}],"constructors":[]}